{"furnitureType": ["Accent Chairs", "Area Rugs", "Bookcases", "Coffee & Cocktail Tables", "Dining Chairs", "Dining Tables", "End Tables", "Kitchen Islands", "Office Chairs", "Ottomans", "Sofas", "Table Lamps", "Teen Bookcases"], "color": ["", "Beige", "Black", "Blue", "Brown", "Gray", "Green", "Purple", "Red", "White", "Yellow"], "matches": ["color", "dimensions", "info", "material", "price"], "navigate_direction": ["Here", "Next", "Previous"], "position": ["center", "left", "right"], "direction": ["back", "down", "front", "left", "right", "up"]}